kubescaler/__init__.py
kubescaler/cluster.py
kubescaler/decorators.py
kubescaler/defaults.py
kubescaler/logger.py
kubescaler/version.py
kubescaler/scaler/__init__.py
kubescaler/scaler/google.py
kubescaler/scaler/aws/__init__.py
kubescaler/scaler/aws/ami.py
kubescaler/scaler/aws/cluster.py
kubescaler/scaler/aws/template.py
kubescaler/scaler/aws/token.py
kubescaler/utils/__init__.py
kubescaler/utils/fileio.py
kubescaler/utils/misc.py
kubescaler/utils/terminal.py
kubescaler-0.0.19.dist-info/LICENSE
kubescaler-0.0.19.dist-info/METADATA
kubescaler-0.0.19.dist-info/NOTICE
kubescaler-0.0.19.dist-info/WHEEL
kubescaler-0.0.19.dist-info/top_level.txt
kubescaler-0.0.19.dist-info/RECORD
