Metadata-Version: 2.1
Name: kubescaler
Version: 0.0.19
Summary: Helper classes for scaling Kubernetes clusters
Home-page: https://github.com/converged-computing/kubescaler
Author: Vanessa Sochat
Author-email: vsoch@users.noreply.github.com
Maintainer: Vanessa Sochat
License: LICENSE
Keywords: Kubernetes,elasticity,scaling,EKS,GKE
Classifier: Intended Audience :: Science/Research
Classifier: Intended Audience :: Developers
Classifier: License :: OSI Approved :: MIT License
Classifier: Programming Language :: Python
Classifier: Topic :: Software Development
Classifier: Topic :: Scientific/Engineering
Classifier: Operating System :: Unix
Classifier: Programming Language :: Python :: 3.8
License-File: LICENSE
License-File: NOTICE
Requires-Dist: ruamel.yaml
Requires-Dist: jsonschema
Requires-Dist: kubernetes
Requires-Dist: google-cloud-container
Requires-Dist: google-api-python-client
Requires-Dist: awscli
Requires-Dist: boto3
Requires-Dist: pytest >=4.6.2
Provides-Extra: aws
Requires-Dist: awscli ; extra == 'aws'
Requires-Dist: boto3 ; extra == 'aws'
Provides-Extra: basic
Requires-Dist: ruamel.yaml ; extra == 'basic'
Requires-Dist: jsonschema ; extra == 'basic'
Requires-Dist: kubernetes ; extra == 'basic'
Provides-Extra: google
Requires-Dist: google-cloud-container ; extra == 'google'
Requires-Dist: google-api-python-client ; extra == 'google'
